{
	"MENU": {
		"position": [0.0, 0.0],
		"scale": [1.0, 1.0],
		
		"background" :
		{
			"position": [0.0, 0.0],
			"scale": [1.0, 1.0],
			"texture": "../Menues/menu1.png"
		},
		
		"files":
		{
			"position": [0.64, 0.0],
			"play":
			{
				"position": [0.0, -0.1],
				"scale": [1.0, 1.0],
				"texture": "../Menues/menu2.png",
				
				"playbutton":
				{
					"position" : [-0.46, 0.36],
					"scale": [0.15, 0.06],
					"text": "Play",
					"color": "FF000000",
					"fontsize" : 30.0
				}
			},
			"options":
			{
				"position": [-0.03, -0.3],
				"scale": [1.0, 1.0],
				"texture": "../Menues/menu2.png",
				
				"optionsbutton":
				{
					"position" : [-0.46, 0.36],
					"scale": [0.15, 0.06],
					"text": "Level editor",
					"color": "FF000000",
					"fontsize" : 30.0
				}
			},
			"exit":
			{
				"position": [-0.06, -0.5],
				"scale": [1.0, 1.0],
				"texture": "../Menues/menu2.png",
				
				"exitbutton":
				{
					"position" : [-0.46, 0.36],
					"scale": [0.15, 0.06],
					"text": "Exit",
					"color": "FF000000",
					"fontsize" : 30.0
				}
			}
		},
		
		"foreground" :
		{
			"position": [0.0, 0.0],
			"scale": [1.0, 1.0],
			"texture": "../Menues/menu3.png"
		}
	},
	"SPLASH" : {},
	"PLAY" : {
		"position": [0.0, 0.0],
		"scale": [1.0, 1.0],
		"paused":
			{
				"position" : [0.0, 0.7],
				"scale": [0.0, 0.0],
				"text": "PAUSED",
				"color": "FF000000",
				"fontsize" : 80.0,
				"centered" : true
			},
		"resume" :
			{
				"position": [0.0, 0.3],
				"scale": [0.1, 0.1],
				"text": "Resume Game",
				"color": "FF000000",
				"fontsize" : 30.0,
				"centered" : true,
				"texture" : "../Menues/Button.png"
			},
		"mainmenu" :
			{
				"position": [0.0, 0.0],
				"scale": [0.1, 0.1],
				"text": "Main Menu",
				"color": "FF000000",
				"fontsize" : 30.0,
				"centered" : true,
				"texture" : "../Menues/Button.png"
			},
		"quit" :
			{
				"position": [0.0, -0.3],
				"scale": [0.1, 0.1],
				"text": "Quit Game",
				"color": "FF000000",
				"fontsize" : 30.0,
				"centered" : true,
				"texture" : "../Menues/Budget.png"
			}
				
	},
	"OPTIONS" : {
		"." :
		{
			"position": [0.0, 0.0],
			"scale": [1.0, 1.0],
			"res_left" :
			{
				"position": [-0.4, 0.0],
				"scale": [0.1, 0.1],
				"texture" : "../Menues/left.png"
			},
			"res_right" :
			{
				"position": [0.4, 0.0],
				"scale": [0.1, 0.1],
				"texture" : "../Menues/left.png"
			},
			"res_content":
			{
				"scale": [0.3, 0.1],
				"texture" : "../Menues/left.png",
				"text" : "LADY GsdasdasdGA",
				"centered" : true
			}
		},
		"." :
		{
			"position": [0.0, 0.2],
			"scale": [1.0, 1.0],
			"res_left" :
			{
				"position": [-0.4, 0.0],
				"scale": [0.1, 0.1],
				"texture" : "../Menues/left.png"
			},
			"res_right" :
			{
				"position": [0.4, 0.0],
				"scale": [0.1, 0.1],
				"texture" : "../Menues/left.png"
			},
			"res_content":
			{
				"scale": [0.3, 0.1],
				"texture" : "floor.png"
			}
		}
	},
"PLACEMENT" : {
  		"Play" :
		{
			"position": [0.9, -0.9],	
			"scale": [0.1, 0.1],
			"texture": "../Menues/Button.png",
			
			"PlayText":
			{
				"position" : [0.97, -0.96],
				"scale": [1.0, 1.0],
				"text": "Play",
				"color": "FF000000",
				"fontsize" : 30.0
			}
		},
		"Trap" :
		{
			"position": [-0.9, 0.9],	
			"scale": [0.1, 0.1],
			"texture": "../Menues/Button.png",
			
			"TrapsText":
			{
				"position" : [0.97, -0.96],
				"scale": [1.0, 1.0],
				"text": "Trap",
				"color": "FF000000",
				"fontsize" : 30.0
			}
		},
		"Guard" :
		{
			"position": [-0.9, 0.7],	
			"scale": [0.1, 0.1],
			"texture": "../Menues/Button.png",
			
			"GuardText":
			{
				"position" : [0.97, -0.96],
				"scale": [1.0, 1.0],
				"text": "Guard",
				"color": "FF000000",
				"fontsize" : 30.0
			}
		},
		"Budget" :
		{
			"position": [0.9, 0.9],	
			"scale": [0.1, 0.1],
			"texture": "../Menues/Budget.png",
			
			"BudgetText":
			{
				"position" : [0.91, -0.96],
				"scale": [1.0, 1.0],
				"text": "Budget:",
				"color": "FF000000",
				"fontsize" : 25.0
			},
			
			"BudgetValue":
			{
				"position" : [1.0, -0.96],
				"scale": [1.0, 1.0],
				"text": "1000",
				"color": "FF000000",
				"fontsize" : 25.0
			}
		}
		
		
				
		
  },
  "LEVELEDIT" : {}
}